MANIFEST.in
README.rst
harstatsgraphite.py
setup.py
harstats_graphite.egg-info/PKG-INFO
harstats_graphite.egg-info/SOURCES.txt
harstats_graphite.egg-info/dependency_links.txt
harstats_graphite.egg-info/top_level.txt
harstats_graphite.egg-info/zip-safe