Metadata-Version: 1.1
Name: harstats-graphite
Version: 0.1.1
Summary: Summarize HAR files and feed them to carbon
Home-page: https://github.com/gvalkov/harstats-graphite
Author: Georgi Valkov
Author-email: georgi.t.valkov@gmail.com
License: New BSD License
Keywords: har graphite carbon
Platform: UNKNOWN
Classifier: Development Status :: 3 - Alpha
Classifier: Programming Language :: Python :: 2.6
Classifier: Programming Language :: Python :: 2.7
Classifier: Programming Language :: Python :: 3.3
Classifier: License :: OSI Approved :: BSD License
Classifier: Intended Audience :: Developers
Classifier: Operating System :: POSIX :: Linux
